edgygraph/__init__.py
edgygraph/graph.py
edgygraph/logging.py
edgygraph/nodes.py
edgygraph/py.typed
edgygraph/rich.py
edgygraph/states.py
edgygraph-0.0.72.dist-info/METADATA
edgygraph-0.0.72.dist-info/WHEEL
edgygraph-0.0.72.dist-info/top_level.txt
edgygraph-0.0.72.dist-info/RECORD
